speech_addons/__init__.py
speech_addons/synth_addons.py
speech_addons/test_synch_addons.py
google_speech_addons-1.0.0.dist-info/LICENSE
google_speech_addons-1.0.0.dist-info/METADATA
google_speech_addons-1.0.0.dist-info/WHEEL
google_speech_addons-1.0.0.dist-info/top_level.txt
google_speech_addons-1.0.0.dist-info/RECORD
